netbox_topology_plugin/__init__.py
netbox_topology_plugin/admin.py
netbox_topology_plugin/filters.py
netbox_topology_plugin/forms.py
netbox_topology_plugin/models.py
netbox_topology_plugin/navigation.py
netbox_topology_plugin/settings.py
netbox_topology_plugin/template_content.py
netbox_topology_plugin/urls.py
netbox_topology_plugin/views.py
netbox_topology_plugin/api/__init__.py
netbox_topology_plugin/api/serializers.py
netbox_topology_plugin/api/urls.py
netbox_topology_plugin/api/views.py
netbox_topology_plugin/constants/__init__.py
netbox_topology_plugin/constants/icons.py
netbox_topology_plugin/constants/interfaces.py
netbox_topology_plugin/migrations/0001_initial.py
netbox_topology_plugin/migrations/0002_alter_savedtopology_id.py
netbox_topology_plugin/migrations/0003_alter_savedtopology_created_by.py
netbox_topology_plugin/migrations/__init__.py
netbox_topology_plugin/static/netbox_topology_plugin/bootstrap.bundle.min.js
netbox_topology_plugin/static/netbox_topology_plugin/bootstrap.min.css
netbox_topology_plugin/static/netbox_topology_plugin/button_utils.js
netbox_topology_plugin/static/netbox_topology_plugin/next_app.js
netbox_topology_plugin/static/netbox_topology_plugin/img/dead_node.png
netbox_topology_plugin/static/netbox_topology_plugin/jquery/jquery-3.5.1.min.js
netbox_topology_plugin/static/netbox_topology_plugin/jquery-ui-1.12.1/jquery-ui.min.js
netbox_topology_plugin/static/netbox_topology_plugin/next_sources/LICENSE.txt
netbox_topology_plugin/static/netbox_topology_plugin/next_sources/css/next.css
netbox_topology_plugin/static/netbox_topology_plugin/next_sources/doc/api.js
netbox_topology_plugin/static/netbox_topology_plugin/next_sources/doc/data.json
netbox_topology_plugin/static/netbox_topology_plugin/next_sources/doc/index.html
netbox_topology_plugin/static/netbox_topology_plugin/next_sources/doc/assets/favicon.ico
netbox_topology_plugin/static/netbox_topology_plugin/next_sources/doc/assets/index.html
netbox_topology_plugin-0.14.3.dist-info/LICENSE
netbox_topology_plugin-0.14.3.dist-info/METADATA
netbox_topology_plugin-0.14.3.dist-info/WHEEL
netbox_topology_plugin-0.14.3.dist-info/top_level.txt
netbox_topology_plugin-0.14.3.dist-info/RECORD
