Metadata-Version: 2.1
Name: netbox-topology-plugin
Version: 0.14.3
Summary: Netbox Topology Plugin, fork of netbox-topology-plugin.  Powered by NextUI
Author-email: Daniel Sheppard <dans@dansheps.com>, Igor Korotchenkov <iDebugAll@gmail.com>
Maintainer-email: Daniel Sheppard <dans@dansheps.com>
License: MIT License
Project-URL: Documentation, https://github.com/dansheps/netbox-topology-plugin/blob/main/README.md
Project-URL: Source, https://github.com/dansheps/netbox-topology-plugin
Project-URL: Tracker, https://github.com/dansheps/netbox-topology-plugin/issues
Keywords: netbox-plugin,netbox-topology
Classifier: Programming Language :: Python :: 3
Requires-Python: >=3.9
License-File: LICENSE
